README.md
setup.py
morerandom/__init__.py
morerandom/morerandom.py
morerandoms.egg-info/PKG-INFO
morerandoms.egg-info/SOURCES.txt
morerandoms.egg-info/dependency_links.txt
morerandoms.egg-info/top_level.txt