Metadata-Version: 1.1
Name: morerandoms
Version: 0.4
Summary: More Random for God of Random!
Home-page: https://github.com/Wolframoviy/morerandom-py
Author: WolframoviyI
Author-email: arseniysstrim@gmail.com
License: MIT
Platform: UNKNOWN
Requires: random
